__init__.py
cmmodule/BED.py
cmmodule/__init__.py
cmmodule/annoGene.py
cmmodule/bgrMerge.py
cmmodule/ireader.py
cmmodule/mapbam.py
cmmodule/mapbed.py
cmmodule/mapgff.py
cmmodule/mapgvcf.py
cmmodule/mapmaf.py
cmmodule/mapregion.py
cmmodule/mapvcf.py
cmmodule/mapwig.py
cmmodule/meta_data.py
cmmodule/myutils.py
cmmodule/sam_header.py
cmmodule/utils.py
cmmodule/wig_reader.py
cmmodule/wiggle.py
CrossMap-0.7.3.dist-info/LICENSE.txt
CrossMap-0.7.3.dist-info/METADATA
CrossMap-0.7.3.dist-info/WHEEL
CrossMap-0.7.3.dist-info/entry_points.txt
CrossMap-0.7.3.dist-info/top_level.txt
CrossMap-0.7.3.dist-info/RECORD
