Metadata-Version: 2.1
Name: CrossMap
Version: 0.7.3
Summary: CrossMap -- Lift over genomics coordinates between assemblies.
Author-email: Liguo Wang <wangliguo78@gmail.com>
Maintainer-email: Liguo Wang <wangliguo78@gmail.com>
License: CrossMap is a program to lift over genome coordinates between different assembly versions.
Project-URL: Documentation, https://crossmap.readthedocs.io/en/latest/
Project-URL: Repository, https://github.com/liguowang/CrossMap.git
Project-URL: Issues, https://github.com/liguowang/CrossMap/issues
Keywords: liftover,genome,coordinates
Classifier: Programming Language :: Python :: 3
Classifier: Development Status :: 4 - Beta
Classifier: License :: OSI Approved :: MIT License
Classifier: Environment :: Console
Classifier: Intended Audience :: Science/Research
Classifier: Operating System :: MacOS :: MacOS X
Classifier: Operating System :: POSIX
Classifier: Topic :: Scientific/Engineering :: Bio-Informatics
Requires-Python: >=3.8
License-File: LICENSE.txt
Requires-Dist: pysam
Requires-Dist: bx-python
Requires-Dist: pyBigWig
